moear_api_common/__init__.py
moear_api_common/base.py
moear_api_common/config.py
moear_api_common/assets/css/base.css
moear_api_common/assets/icons/delete.jpg
moear_api_common/assets/images/cv_default.jpg
moear_api_common/assets/images/mh_default.gif
moear_api_common/utils/__init__.py
moear_api_common/utils/img.py
moear_api_common/utils/kindlegen.py
moear_api_common-1.0.2.post2.dist-info/METADATA
moear_api_common-1.0.2.post2.dist-info/RECORD
moear_api_common-1.0.2.post2.dist-info/WHEEL
moear_api_common-1.0.2.post2.dist-info/top_level.txt
