Metadata-Version: 2.1
Name: moear-api-common
Version: 1.0.2.post2
Summary: 为MoEar扩展插件提供接口定义以及通用组件
Home-page: https://github.com/littlemo/moear-api-common
Author: moear developers
Author-email: moore@moorehy.com
Maintainer: littlemo
Maintainer-email: moore@moorehy.com
License: GPLv3
Project-URL: Tracker, https://github.com/littlemo/moear-api-common/issues
Project-URL: Documentation, http://moear-api-common.rtfd.io/
Project-URL: Source, https://github.com/littlemo/moear-api-common
Keywords: moear api
Platform: UNKNOWN
Classifier: Development Status :: 3 - Alpha
Classifier: Environment :: Console
Classifier: Environment :: MacOS X
Classifier: Intended Audience :: Developers
Classifier: License :: OSI Approved :: GNU General Public License v3 (GPLv3)
Classifier: Natural Language :: Chinese (Simplified)
Classifier: Operating System :: MacOS
Classifier: Operating System :: POSIX :: Linux
Classifier: Programming Language :: Python :: 3
Classifier: Programming Language :: Python :: 3 :: Only
Classifier: Programming Language :: Python :: 3.5
Classifier: Topic :: Communications :: Email
Classifier: Topic :: Documentation :: Sphinx
Classifier: Topic :: Internet
Classifier: Topic :: Software Development :: Version Control :: Git
Classifier: Topic :: Software Development :: Libraries :: Python Modules
Classifier: Topic :: System :: Networking
Classifier: Topic :: Terminals
Classifier: Topic :: Utilities
Requires-Python: >=3
Requires-Dist: six (~=1.11.0)
Requires-Dist: Pillow (~=5.0.0)
